walnut_kernel/__init__.py
walnut_kernel/__main__.py
walnut_kernel/_version.py
walnut_kernel/config.py
walnut_kernel/kernel.py
walnut_kernel/magic.py
walnut_kernel-0.3.3.data/data/share/jupyter/kernels/walnut/kernel.json
walnut_kernel-0.3.3.dist-info/METADATA
walnut_kernel-0.3.3.dist-info/WHEEL
walnut_kernel-0.3.3.dist-info/licenses/LICENSE
walnut_kernel-0.3.3.dist-info/RECORD
