Metadata-Version: 2.4
Name: walnut-kernel
Version: 0.3.3
Summary: Simple kernel for Walnut
Project-URL: Homepage, https://github.com/nopid/walnut_kernel
Maintainer-email: Nicolas Ollinger <nopid@free.fr>
License: CeCILL License
License-File: LICENSE
Classifier: Intended Audience :: Developers
Classifier: License :: OSI Approved :: BSD License
Classifier: Programming Language :: Python :: 3
Requires-Python: >=3.9
Requires-Dist: ipykernel
Requires-Dist: jupyter-client
Requires-Dist: licofage
Requires-Dist: metakernel
Requires-Dist: ratser
